LICENSE
README.md
setup.py
src/BotForge/__init__.py
src/BotForge/command_context.py
src/BotForge/login.py
src/BotForge.egg-info/PKG-INFO
src/BotForge.egg-info/SOURCES.txt
src/BotForge.egg-info/dependency_links.txt
src/BotForge.egg-info/top_level.txt
tests/test_pygram.py