Metadata-Version: 2.1
Name: BotForge
Version: 0.0.3
Summary: BotForge - tiny bot api for telegram
Home-page: https://github.com/KailUser/BotForge
Author: Syirezz
Author-email: syirezz@icloud.com
License: MIT
Classifier: Programming Language :: Python :: 3.8
Classifier: License :: OSI Approved :: MIT License
Classifier: Operating System :: OS Independent
License-File: LICENSE
